PyFDown/__init__.py
PyFDown/download.py
PyFDown/test.py
PyFDown-0.1.2.dist-info/LICENSE
PyFDown-0.1.2.dist-info/METADATA
PyFDown-0.1.2.dist-info/WHEEL
PyFDown-0.1.2.dist-info/top_level.txt
PyFDown-0.1.2.dist-info/RECORD
