Metadata-Version: 2.1
Name: PyFDown
Version: 0.1.2
Summary: A fast downloader with Python
Home-page: https://github.com/Nemo2011/PyFDown
Author: Nemo2011
Author-email: yimoxia@outlook.com
License: LGPLv3
Platform: UNKNOWN
License-File: LICENSE
Requires-Dist: requests
Requires-Dist: tqdm
Requires-Dist: multitasking
Requires-Dist: retry
